rstb/__init__.py
rstb/__main__.py
rstb/_version.py
rstb/resource_factory_info.tsv
rstb/rstb.py
rstb/util.py
rstb-1.2.1.dist-info/LICENSE
rstb-1.2.1.dist-info/METADATA
rstb-1.2.1.dist-info/WHEEL
rstb-1.2.1.dist-info/entry_points.txt
rstb-1.2.1.dist-info/top_level.txt
rstb-1.2.1.dist-info/RECORD
