Metadata-Version: 2.1
Name: rstb
Version: 1.2.1
Summary: Breath of the Wild RSTB parser and editing tool
Home-page: https://github.com/leoetlino/rstb
Author: leoetlino
Author-email: leo@leolam.fr
License: UNKNOWN
Platform: UNKNOWN
Classifier: License :: OSI Approved :: GNU General Public License v2 or later (GPLv2+)
Classifier: Operating System :: OS Independent
Classifier: Programming Language :: Python :: 3 :: Only
Classifier: Topic :: Software Development :: Libraries
Requires-Python: >=3.6
Requires-Dist: syaz0 (~=1.0)
